falcon_resource_factory/__init__.py
falcon_resource_factory/factory.py
falcon_resource_factory/utils.py
falcon_resource_factory-0.0.2.dist-info/DESCRIPTION.rst
falcon_resource_factory-0.0.2.dist-info/METADATA
falcon_resource_factory-0.0.2.dist-info/RECORD
falcon_resource_factory-0.0.2.dist-info/WHEEL
falcon_resource_factory-0.0.2.dist-info/metadata.json
falcon_resource_factory-0.0.2.dist-info/top_level.txt
