Metadata-Version: 2.0
Name: falcon-resource-factory
Version: 0.0.2
Summary: A simple falcon library that allows defining a single resource class to handle requests for a single item as well as multiple items
Home-page: https://github.com/loanzen/falcon-resource-factory
Author: Ritesh Kadmawala
Author-email: ritesh@loanzen.in
License: MIT
Platform: UNKNOWN
Requires-Dist: falcon
